nonebot_plugin_looklike/__init__.py
nonebot_plugin_looklike/utils.py
nonebot_plugin_looklike-0.0.3.dist-info/LICENSE
nonebot_plugin_looklike-0.0.3.dist-info/METADATA
nonebot_plugin_looklike-0.0.3.dist-info/WHEEL
nonebot_plugin_looklike-0.0.3.dist-info/RECORD
